{
  "AWSTemplateFormatVersion": "2010-09-09",
  "Description": "The AWS CloudFormation template for this Serverless application",
  "Resources": {
    "ServerlessDeploymentBucket": {
      "Type": "AWS::S3::Bucket",
      "Properties": {
        "BucketEncryption": {
          "ServerSideEncryptionConfiguration": [
            {
              "ServerSideEncryptionByDefault": {
                "SSEAlgorithm": "AES256"
              }
            }
          ]
        }
      }
    },
    "ServerlessDeploymentBucketPolicy": {
      "Type": "AWS::S3::BucketPolicy",
      "Properties": {
        "Bucket": {
          "Ref": "ServerlessDeploymentBucket"
        },
        "PolicyDocument": {
          "Statement": [
            {
              "Action": "s3:*",
              "Effect": "Deny",
              "Principal": "*",
              "Resource": [
                {
                  "Fn::Join": [
                    "",
                    [
                      "arn:",
                      {
                        "Ref": "AWS::Partition"
                      },
                      ":s3:::",
                      {
                        "Ref": "ServerlessDeploymentBucket"
                      },
                      "/*"
                    ]
                  ]
                },
                {
                  "Fn::Join": [
                    "",
                    [
                      "arn:",
                      {
                        "Ref": "AWS::Partition"
                      },
                      ":s3:::",
                      {
                        "Ref": "ServerlessDeploymentBucket"
                      }
                    ]
                  ]
                }
              ],
              "Condition": {
                "Bool": {
                  "aws:SecureTransport": false
                }
              }
            }
          ]
        }
      }
    },
    "ApiLogGroup": {
      "Type": "AWS::Logs::LogGroup",
      "Properties": {
        "LogGroupName": "/aws/lambda/loan-backend-dev-api"
      }
    },
    "IamRoleLambdaExecution": {
      "Type": "AWS::IAM::Role",
      "Properties": {
        "AssumeRolePolicyDocument": {
          "Version": "2012-10-17",
          "Statement": [
            {
              "Effect": "Allow",
              "Principal": {
                "Service": [
                  "lambda.amazonaws.com"
                ]
              },
              "Action": [
                "sts:AssumeRole"
              ]
            }
          ]
        },
        "Policies": [
          {
            "PolicyName": {
              "Fn::Join": [
                "-",
                [
                  "loan-backend",
                  "dev",
                  "lambda"
                ]
              ]
            },
            "PolicyDocument": {
              "Version": "2012-10-17",
              "Statement": [
                {
                  "Effect": "Allow",
                  "Action": [
                    "logs:CreateLogStream",
                    "logs:CreateLogGroup",
                    "logs:TagResource"
                  ],
                  "Resource": [
                    {
                      "Fn::Sub": "arn:${AWS::Partition}:logs:${AWS::Region}:${AWS::AccountId}:log-group:/aws/lambda/loan-backend-dev*:*"
                    }
                  ]
                },
                {
                  "Effect": "Allow",
                  "Action": [
                    "logs:PutLogEvents"
                  ],
                  "Resource": [
                    {
                      "Fn::Sub": "arn:${AWS::Partition}:logs:${AWS::Region}:${AWS::AccountId}:log-group:/aws/lambda/loan-backend-dev*:*:*"
                    }
                  ]
                }
              ]
            }
          }
        ],
        "Path": "/",
        "RoleName": {
          "Fn::Join": [
            "-",
            [
              "loan-backend",
              "dev",
              {
                "Ref": "AWS::Region"
              },
              "lambdaRole"
            ]
          ]
        }
      }
    },
    "ApiLambdaFunction": {
      "Type": "AWS::Lambda::Function",
      "Properties": {
        "Code": {
          "S3Bucket": {
            "Ref": "ServerlessDeploymentBucket"
          },
          "S3Key": "serverless/loan-backend/dev/1765443137832-2025-12-11T08:52:17.832Z/loan-backend.zip"
        },
        "Handler": "api/index.handler",
        "Runtime": "nodejs18.x",
        "FunctionName": "loan-backend-dev-api",
        "MemorySize": 1024,
        "Timeout": 6,
        "Environment": {
          "Variables": {
            "PORT": "4000",
            "MONGO_URI": "mongodb+srv://user1:peasrip12345@cluster0.p7baflk.mongodb.net/?appName=Cluster0",
            "JWT_SECRET": "123456",
            "JWT_EXPIRES_IN": "7d",
            "ADMIN_USERNAME": "admin",
            "ADMIN_PASSWORD": "admin123"
          }
        },
        "Role": {
          "Fn::GetAtt": [
            "IamRoleLambdaExecution",
            "Arn"
          ]
        }
      },
      "DependsOn": [
        "ApiLogGroup"
      ]
    },
    "ApiLambdaVersionoU3BRr8De6lNYlYaasEDCJyI5NcAMm3z8hwwc3JlsKU": {
      "Type": "AWS::Lambda::Version",
      "DeletionPolicy": "Retain",
      "Properties": {
        "FunctionName": {
          "Ref": "ApiLambdaFunction"
        },
        "CodeSha256": "o4m1yGmX/WCKB2VJCSbY02zgNq7tXsEaDAtfC9myW1g="
      }
    },
    "HttpApi": {
      "Type": "AWS::ApiGatewayV2::Api",
      "Properties": {
        "Name": "dev-loan-backend",
        "ProtocolType": "HTTP",
        "CorsConfiguration": {
          "AllowCredentials": true,
          "AllowHeaders": [
            "Content-Type",
            "Authorization"
          ],
          "AllowMethods": [
            "GET",
            "POST",
            "PUT",
            "DELETE",
            "OPTIONS"
          ],
          "AllowOrigins": [
            "http://localhost:8080",
            "https://admin-rs1h.onrender.com"
          ]
        }
      }
    },
    "HttpApiStage": {
      "Type": "AWS::ApiGatewayV2::Stage",
      "Properties": {
        "ApiId": {
          "Ref": "HttpApi"
        },
        "StageName": "$default",
        "AutoDeploy": true,
        "DefaultRouteSettings": {
          "DetailedMetricsEnabled": false
        }
      }
    },
    "ApiLambdaPermissionHttpApi": {
      "Type": "AWS::Lambda::Permission",
      "Properties": {
        "FunctionName": {
          "Fn::GetAtt": [
            "ApiLambdaFunction",
            "Arn"
          ]
        },
        "Action": "lambda:InvokeFunction",
        "Principal": "apigateway.amazonaws.com",
        "SourceArn": {
          "Fn::Join": [
            "",
            [
              "arn:",
              {
                "Ref": "AWS::Partition"
              },
              ":execute-api:",
              {
                "Ref": "AWS::Region"
              },
              ":",
              {
                "Ref": "AWS::AccountId"
              },
              ":",
              {
                "Ref": "HttpApi"
              },
              "/*"
            ]
          ]
        }
      }
    },
    "HttpApiIntegrationApi": {
      "Type": "AWS::ApiGatewayV2::Integration",
      "Properties": {
        "ApiId": {
          "Ref": "HttpApi"
        },
        "IntegrationType": "AWS_PROXY",
        "IntegrationUri": {
          "Fn::GetAtt": [
            "ApiLambdaFunction",
            "Arn"
          ]
        },
        "PayloadFormatVersion": "2.0",
        "TimeoutInMillis": 30000
      }
    },
    "HttpApiRouteAnyProxyVar": {
      "Type": "AWS::ApiGatewayV2::Route",
      "Properties": {
        "ApiId": {
          "Ref": "HttpApi"
        },
        "RouteKey": "ANY /{proxy+}",
        "Target": {
          "Fn::Join": [
            "/",
            [
              "integrations",
              {
                "Ref": "HttpApiIntegrationApi"
              }
            ]
          ]
        }
      },
      "DependsOn": "HttpApiIntegrationApi"
    }
  },
  "Outputs": {
    "ServerlessDeploymentBucketName": {
      "Value": {
        "Ref": "ServerlessDeploymentBucket"
      },
      "Export": {
        "Name": "sls-loan-backend-dev-ServerlessDeploymentBucketName"
      }
    },
    "ApiLambdaFunctionQualifiedArn": {
      "Description": "Current Lambda function version",
      "Value": {
        "Ref": "ApiLambdaVersionoU3BRr8De6lNYlYaasEDCJyI5NcAMm3z8hwwc3JlsKU"
      },
      "Export": {
        "Name": "sls-loan-backend-dev-ApiLambdaFunctionQualifiedArn"
      }
    },
    "HttpApiId": {
      "Description": "Id of the HTTP API",
      "Value": {
        "Ref": "HttpApi"
      },
      "Export": {
        "Name": "sls-loan-backend-dev-HttpApiId"
      }
    },
    "HttpApiUrl": {
      "Description": "URL of the HTTP API",
      "Value": {
        "Fn::Join": [
          "",
          [
            "https://",
            {
              "Ref": "HttpApi"
            },
            ".execute-api.",
            {
              "Ref": "AWS::Region"
            },
            ".",
            {
              "Ref": "AWS::URLSuffix"
            }
          ]
        ]
      },
      "Export": {
        "Name": "sls-loan-backend-dev-HttpApiUrl"
      }
    }
  }
}